LICENSE
MANIFEST.in
setup.py
docs/Makefile
docs/adapters.rst
docs/complete_reference.rst
docs/conf.py
docs/context.rst
docs/function.rst
docs/function_manager.rst
docs/getting_started_part_1.rst
docs/getting_started_part_2.rst
docs/index.rst
docs/integration_tests.rst
docs/introduction.rst
docs/libpeerconnection.log
docs/make.bat
docs/protocol.rst
docs/request_response.rst
docs/running_tests.rst
docs/server.rst
docs/test_bench.rst
docs/working_with_pyws.rst
examples/Makefile.common
examples/__init__.py
examples/api_settings.py
examples/api_settings.pyc
examples/authenticate.py
examples/authenticate.pyc
examples/functions.py
examples/functions.pyc
examples/server.py
examples/server.pyc
examples/server_dirs
examples/_django/Makefile
examples/_django/__init__.py
examples/_django/__init__.pyc
examples/_django/manage.py
examples/_django/settings.py
examples/_django/settings.pyc
examples/_django/test_form.py
examples/_django/test_form.pyc
examples/_django/urls.py
examples/_django/urls.pyc
examples/_django/templates/test_form.html
examples/_twisted/__init__.py
examples/_wsgi/Makefile
examples/_wsgi/__init__.py
src/pyws/__init__.py
src/pyws/errors.py
src/pyws/request.py
src/pyws/response.py
src/pyws/server.py
src/pyws/settings.py
src/pyws/utils.py
src/pyws.egg-info/PKG-INFO
src/pyws.egg-info/SOURCES.txt
src/pyws.egg-info/dependency_links.txt
src/pyws.egg-info/requires.txt
src/pyws.egg-info/top_level.txt
src/pyws/adapters/__init__.py
src/pyws/adapters/_django.py
src/pyws/adapters/_twisted.py
src/pyws/adapters/_wsgi.py
src/pyws/functions/__init__.py
src/pyws/functions/managers.py
src/pyws/functions/register.py
src/pyws/functions/args/__init__.py
src/pyws/functions/args/field.py
src/pyws/functions/args/types/__init__.py
src/pyws/functions/args/types/base.py
src/pyws/functions/args/types/complex.py
src/pyws/functions/args/types/simple.py
src/pyws/protocols/__init__.py
src/pyws/protocols/base.py
src/pyws/protocols/rest.py
src/pyws/protocols/soap/__init__.py
src/pyws/protocols/soap/utils.py
src/pyws/protocols/soap/wsdl.py
src/pyws/protocols/soap/xsd.py
tests/Makefile
tests/Makefile.common
tests/run_doctests.py
tests/java/Makefile
