Metadata-Version: 1.0
Name: pyws
Version: 1.1.5
Summary: Python SOAP server providing WSDL
Home-page: https://github.com/stepank/pyws
Author: Stepan N. Kornyakov
Author-email: stepankk@gmail.com
License: MIT
Keywords: soap,wsdl,server,xml,json,web services
Platform: Any
